db_hj3415/__init__.py
db_hj3415/cli.py
db_hj3415/mymongo/__init__.py
db_hj3415/mymongo/ai_report.py
db_hj3415/mymongo/base.py
db_hj3415/mymongo/c101.py
db_hj3415/mymongo/c103.py
db_hj3415/mymongo/c1034.py
db_hj3415/mymongo/c104.py
db_hj3415/mymongo/c106.py
db_hj3415/mymongo/c108.py
db_hj3415/mymongo/corps.py
db_hj3415/mymongo/dart.py
db_hj3415/mymongo/flask.py
db_hj3415/mymongo/logs.py
db_hj3415/mymongo/mi.py
db_hj3415/myredis/__init__.py
db_hj3415/myredis/base.py
db_hj3415/myredis/c101.py
db_hj3415/myredis/c1034.py
db_hj3415/myredis/c106.py
db_hj3415/myredis/c108.py
db_hj3415/myredis/corps.py
db_hj3415/myredis/dart.py
db_hj3415/myredis/dart_today.py
db_hj3415/myredis/mi.py
db_hj3415-4.9.5.dist-info/entry_points.txt
db_hj3415-4.9.5.dist-info/WHEEL
db_hj3415-4.9.5.dist-info/METADATA
db_hj3415-4.9.5.dist-info/RECORD
