Metadata-Version: 2.4
Name: db_hj3415
Version: 4.9.5
Summary: Manage db modules
Author-email: Hyungjin Kim <hj3415@gmail.com>
Classifier: License :: OSI Approved :: MIT License
Requires-Dist: pandas>=2.2.3
Requires-Dist: pymongo>=4.10.1
Requires-Dist: scraper-hj3415>=4.8.1
Requires-Dist: utils-hj3415>=3.2.0
Requires-Dist: cryptography>=43.0.0
Requires-Dist: redis>=5.0.8
Requires-Dist: SQLAlchemy>=2.0.34
Requires-Dist: chatgpt_hj3415>=0.1.5
Project-URL: Home, https://www.hyungjin.kr
